{
  "resourceSpans": [
    {
      "resource": {
        "attributes": [
          {
            "key": "service.name",
            "value": {
              "stringValue": "orderService"
            }
          }
        ]
      },
      "scopeSpans": [
        {
          "scope": {
            "name": "order-service-tracer"
          },
          "spans": [
            {
              "traceId": "0102030405060708090a0b0c0d0e0f10",
              "spanId": "1011121314151617",
              "name": "createOrder",
              "startTimeUnixNano": "1693910000000000000",
              "endTimeUnixNano": "1693910000100000000",
              "attributes": [
                {
                  "key": "http.status_code",
                  "value": {
                    "intValue": "201"
                  }
                }
              ],
              "status": {
                "code": 1
              }
            }
          ]
        }
      ]
    },
    {
      "resource": {
        "attributes": [
          {
            "key": "service.name",
            "value": {
              "stringValue": "inventoryService"
            }
          }
        ]
      },
      "scopeSpans": [
        {
          "scope": {
            "name": "inventory-service-tracer"
          },
          "spans": [
            {
              "traceId": "0102030405060708090a0b0c0d0e0f10",
              "spanId": "2021222324252627",
              "parentSpanId": "1011121314151617",
              "name": "reserveInventory",
              "startTimeUnixNano": "1693910000150000000",
              "endTimeUnixNano": "1693910000250000000",
              "attributes": [
                {
                  "key": "http.status_code",
                  "value": {
                    "intValue": "200"
                  }
                }
              ],
              "status": {
                "code": 1
              }
            }
          ]
        }
      ]
    },
    {
      "resource": {
        "attributes": [
          {
            "key": "service.name",
            "value": {
              "stringValue": "riskService"
            }
          }
        ]
      },
      "scopeSpans": [
        {
          "scope": {
            "name": "risk-service-tracer"
          },
          "spans": [
            {
              "traceId": "0102030405060708090a0b0c0d0e0f10",
              "spanId": "4041424344454647",
              "parentSpanId": "1011121314151617",
              "name": "check",
              "startTimeUnixNano": "1693910000160000000",
              "endTimeUnixNano": "1693910000240000000",
              "attributes": [
                {
                  "key": "http.status_code",
                  "value": {
                    "intValue": "200"
                  }
                }
              ],
              "status": {
                "code": 1
              }
            }
          ]
        }
      ]
    },
    {
      "resource": {
        "attributes": [
          {
            "key": "service.name",
            "value": {
              "stringValue": "shippingService"
            }
          }
        ]
      },
      "scopeSpans": [
        {
          "scope": {
            "name": "shipping-service-tracer"
          },
          "spans": [
            {
              "traceId": "0102030405060708090a0b0c0d0e0f10",
              "spanId": "3031323334353637",
              "parentSpanId": "1011121314151617",
              "name": "createShipment",
              "startTimeUnixNano": "1693910000300000000",
              "endTimeUnixNano": "1693910000400000000",
              "attributes": [
                {
                  "key": "http.status_code",
                  "value": {
                    "intValue": "201"
                  }
                }
              ],
              "status": {
                "code": 1
              }
            }
          ]
        }
      ]
    }
  ]
}